NPerlinNoise/__init__.py
NPerlinNoise/__main__.py
NPerlinNoise/config.toml
NPerlinNoise/generator.py
NPerlinNoise/nPerlin.py
NPerlinNoise/noise.py
NPerlinNoise/selectionTools.py
NPerlinNoise/tools.py
nPerlinNoise-0.1.4a0.dist-info/LICENSE
nPerlinNoise-0.1.4a0.dist-info/METADATA
nPerlinNoise-0.1.4a0.dist-info/WHEEL
nPerlinNoise-0.1.4a0.dist-info/entry_points.txt
nPerlinNoise-0.1.4a0.dist-info/top_level.txt
nPerlinNoise-0.1.4a0.dist-info/RECORD
