Metadata-Version: 2.1
Name: nPerlinNoise
Version: 0.1.4a0
Summary: A robust open source implementation of Perlin Noise Algorithm for N-Dimensions
Author-email: Amith225 <amitharun3@gmail.com>
Maintainer-email: Amith225 <amitharun3@gmail.com>
License: MIT License        
Project-URL: homepage, https://pypi.org/project/nPerlinNoise/
Project-URL: repository, https://github.com/Amith225/nPerlinNoise
Keywords: perlin-noise,perlin,n-dimensional,numpy-perlin,numpy-noise,noise,noise-algorithm,performance
Classifier: License :: OSI Approved :: MIT License
Classifier: Programming Language :: Python
Classifier: Programming Language :: Python :: 3.10
Requires-Python: >=3.10
License-File: LICENSE
Requires-Dist: numexpr (>=2.8.3)
Requires-Dist: numpy (>=1.23.3)
Provides-Extra: dev
Requires-Dist: matplotlib (>=3.6.1) ; extra == 'dev'
Requires-Dist: plotly (>=5.10.0) ; extra == 'dev'
Requires-Dist: PyQt5 (>=5.15.7) ; extra == 'dev'
Requires-Dist: PyQt5-stubs (>=5.15.6.0) ; extra == 'dev'
Requires-Dist: build (>=0.8.0) ; extra == 'dev'
Requires-Dist: twine (>=4.0.1) ; extra == 'dev'
